nonebot_plugin_acgnshow-0.3.dist-info/METADATA
nonebot_plugin_acgnshow-0.3.dist-info/WHEEL
nonebot_plugin_acgnshow-0.3.dist-info/entry_points.txt
nonebot_plugin_acgnshow-0.3.dist-info/licenses/LICENSE
nonebot_plugin_acgnshow/__init__.py
nonebot_plugin_acgnshow/acgnapis.py
nonebot_plugin_acgnshow/acgnshower.py
nonebot_plugin_acgnshow/config.py
nonebot_plugin_acgnshow/models.py
nonebot_plugin_acgnshow/res/SourceHanSans.otf
nonebot_plugin_acgnshow/res/bgimage/bg1.webp
nonebot_plugin_acgnshow/res/bgimage/bg2.webp
nonebot_plugin_acgnshow/res/bgimage/bg3.webp
nonebot_plugin_acgnshow/res/bgimage/bg4.webp
nonebot_plugin_acgnshow/res/bgimage/bg5.webp
nonebot_plugin_acgnshow/res/bgimage/bg6.webp
nonebot_plugin_acgnshow/res/bgimage/bg7.webp
nonebot_plugin_acgnshow/res/css/detail.css
nonebot_plugin_acgnshow/res/css/style.css
nonebot_plugin_acgnshow/res/details.html
nonebot_plugin_acgnshow/res/svg/no.svg
nonebot_plugin_acgnshow/res/svg/yes.svg
nonebot_plugin_acgnshow/res/template.html
nonebot_plugin_acgnshow/util.py
nonebot_plugin_acgnshow-0.3.dist-info/RECORD
