Metadata-Version: 2.1
Name: nonebot-plugin-acgnshow
Version: 0.3
Summary: Nonebot2插件，从哔哩哔哩会员购获取简易展览数据
Author-Email: Asankilp <asankilp@outlook.com>
License: MIT
Project-URL: Homepage, https://github.com/LiteyukiStudio/nonebot-plugin-acgnshow
Requires-Python: <4.0,>=3.9
Requires-Dist: nonebot2>=2.2.0
Requires-Dist: nonebot-plugin-alconna>=0.48.0
Requires-Dist: nonebot-plugin-htmlrender>=0.3.2
Requires-Dist: jinja2>=3.1.4
Requires-Dist: aiohttp>=3.9
